nbclean/__init__.py
nbclean/clean.py
nbclean/preprocessors.py
nbclean/run.py
nbclean/utils.py
nbclean/tests/test_nbclean.py
nbclean-0.3.2.dist-info/LICENSE
nbclean-0.3.2.dist-info/WHEEL
nbclean-0.3.2.dist-info/METADATA
nbclean-0.3.2.dist-info/RECORD
