Metadata-Version: 1.1
Name: nbclean
Version: 0.3.2
Summary: Tools for preprocessing and cleaning Jupyter Notebooks.
Home-page: https://predictablynoisy.com/nbclean
Author: Chris Holdgraf
Author-email: choldgraf@berkeley.edu
